setup.py
regression_diagnostics/__init__.py
regression_diagnostics/regression_diagnostics.py
regression_diagnostics.egg-info/PKG-INFO
regression_diagnostics.egg-info/SOURCES.txt
regression_diagnostics.egg-info/dependency_links.txt
regression_diagnostics.egg-info/not-zip-safe
regression_diagnostics.egg-info/top_level.txt