Metadata-Version: 1.0
Name: regression-diagnostics
Version: 0.1
Summary: Package for doing Regression Diagnostics in Python
Home-page: UNKNOWN
Author: Tyler Watkins
Author-email: tylerwatkins101@gmail.com
License: UNKNOWN
Platform: UNKNOWN
